Workbook

Sheet Bond Toolkit
A1: Interest Rate / Bond Cash-Flow Toolkit
A2: Blue = inputs. Black = formulas. Change inputs → outputs/cash-flows update. Use 'Run Scenarios' VBA to fill scenario table.
A4: INPUTS
A5: Face Value (FV) | B5: 1000 | D5: Max rows in CF table | E5: 200
A6: Annual Coupon Rate (c) | B6: 0.05 | D6: DERIVED (do not edit)
A7: Maturity (years, T) | B7: 10 | D7: Coupon per period | E7: =B5*B6/B8
A8: Coupon Frequency (p payments/year) | B8: 2 | D8: Number of payments N | E8: =B7*B8
A9: Yield Nominal Rate j^(m) | B9: 0.06 | D9: a = 1 + j/m | E9: =1+B9/B10
A10: Yield Compounding (m times/year) | B10: 2 | D10: Base price P0 | E10: =B13
D11: Python v2: optionally define a Curve sheet (pillars + zero rates) for curve pricing/scenarios.
A12: OUTPUTS
A13: Bond Price / PV (P) | B13: =SUM(E19:E218)
A14: Macaulay Duration (years) | B14: =IF(B13=0,"",SUMPRODUCT(B19:B218,E19:E218)/B13)
A15: Modified Duration (years) | B15: =IF(B14="","",B14/(1+B9/B10))
A16: Convexity (years^2) | B16: =IF(B13=0,"",SUMPRODUCT(B19:B218,(B19:B218+1/B10),E19:E218)/(B13*(1+B9/B10)^2))
A18: k | B18: Time t (yrs) | C18: Cash Flow | D18: Discount Factor | E18: PV
A19: =IF(1<= $E$8, 1, "") | B19: =IF(A19="","",A19/$B$8) | C19: =IF(A19="","",IF(A19<$E$8,$E$7,$E$7+$B$5)) | D19: =IF(A19="","",$E$9^(-$B$10*B19)) | E19: =IF(A19="","",C19*D19)
A20: =IF(2<= $E$8, 2, "") | B20: =IF(A20="","",A20/$B$8) | C20: =IF(A20="","",IF(A20<$E$8,$E$7,$E$7+$B$5)) | D20: =IF(A20="","",$E$9^(-$B$10*B20)) | E20: =IF(A20="","",C20*D20)
A21: =IF(3<= $E$8, 3, "") | B21: =IF(A21="","",A21/$B$8) | C21: =IF(A21="","",IF(A21<$E$8,$E$7,$E$7+$B$5)) | D21: =IF(A21="","",$E$9^(-$B$10*B21)) | E21: =IF(A21="","",C21*D21)
A22: =IF(4<= $E$8, 4, "") | B22: =IF(A22="","",A22/$B$8) | C22: =IF(A22="","",IF(A22<$E$8,$E$7,$E$7+$B$5)) | D22: =IF(A22="","",$E$9^(-$B$10*B22)) | E22: =IF(A22="","",C22*D22)
A23: =IF(5<= $E$8, 5, "") | B23: =IF(A23="","",A23/$B$8) | C23: =IF(A23="","",IF(A23<$E$8,$E$7,$E$7+$B$5)) | D23: =IF(A23="","",$E$9^(-$B$10*B23)) | E23: =IF(A23="","",C23*D23)
A24: =IF(6<= $E$8, 6, "") | B24: =IF(A24="","",A24/$B$8) | C24: =IF(A24="","",IF(A24<$E$8,$E$7,$E$7+$B$5)) | D24: =IF(A24="","",$E$9^(-$B$10*B24)) | E24: =IF(A24="","",C24*D24)
A25: =IF(7<= $E$8, 7, "") | B25: =IF(A25="","",A25/$B$8) | C25: =IF(A25="","",IF(A25<$E$8,$E$7,$E$7+$B$5)) | D25: =IF(A25="","",$E$9^(-$B$10*B25)) | E25: =IF(A25="","",C25*D25)
A26: =IF(8<= $E$8, 8, "") | B26: =IF(A26="","",A26/$B$8) | C26: =IF(A26="","",IF(A26<$E$8,$E$7,$E$7+$B$5)) | D26: =IF(A26="","",$E$9^(-$B$10*B26)) | E26: =IF(A26="","",C26*D26)
A27: =IF(9<= $E$8, 9, "") | B27: =IF(A27="","",A27/$B$8) | C27: =IF(A27="","",IF(A27<$E$8,$E$7,$E$7+$B$5)) | D27: =IF(A27="","",$E$9^(-$B$10*B27)) | E27: =IF(A27="","",C27*D27)
A28: =IF(10<= $E$8, 10, "") | B28: =IF(A28="","",A28/$B$8) | C28: =IF(A28="","",IF(A28<$E$8,$E$7,$E$7+$B$5)) | D28: =IF(A28="","",$E$9^(-$B$10*B28)) | E28: =IF(A28="","",C28*D28)
A29: =IF(11<= $E$8, 11, "") | B29: =IF(A29="","",A29/$B$8) | C29: =IF(A29="","",IF(A29<$E$8,$E$7,$E$7+$B$5)) | D29: =IF(A29="","",$E$9^(-$B$10*B29)) | E29: =IF(A29="","",C29*D29)
A30: =IF(12<= $E$8, 12, "") | B30: =IF(A30="","",A30/$B$8) | C30: =IF(A30="","",IF(A30<$E$8,$E$7,$E$7+$B$5)) | D30: =IF(A30="","",$E$9^(-$B$10*B30)) | E30: =IF(A30="","",C30*D30)
A31: =IF(13<= $E$8, 13, "") | B31: =IF(A31="","",A31/$B$8) | C31: =IF(A31="","",IF(A31<$E$8,$E$7,$E$7+$B$5)) | D31: =IF(A31="","",$E$9^(-$B$10*B31)) | E31: =IF(A31="","",C31*D31)
A32: =IF(14<= $E$8, 14, "") | B32: =IF(A32="","",A32/$B$8) | C32: =IF(A32="","",IF(A32<$E$8,$E$7,$E$7+$B$5)) | D32: =IF(A32="","",$E$9^(-$B$10*B32)) | E32: =IF(A32="","",C32*D32)
A33: =IF(15<= $E$8, 15, "") | B33: =IF(A33="","",A33/$B$8) | C33: =IF(A33="","",IF(A33<$E$8,$E$7,$E$7+$B$5)) | D33: =IF(A33="","",$E$9^(-$B$10*B33)) | E33: =IF(A33="","",C33*D33)
A34: =IF(16<= $E$8, 16, "") | B34: =IF(A34="","",A34/$B$8) | C34: =IF(A34="","",IF(A34<$E$8,$E$7,$E$7+$B$5)) | D34: =IF(A34="","",$E$9^(-$B$10*B34)) | E34: =IF(A34="","",C34*D34)
A35: =IF(17<= $E$8, 17, "") | B35: =IF(A35="","",A35/$B$8) | C35: =IF(A35="","",IF(A35<$E$8,$E$7,$E$7+$B$5)) | D35: =IF(A35="","",$E$9^(-$B$10*B35)) | E35: =IF(A35="","",C35*D35)
A36: =IF(18<= $E$8, 18, "") | B36: =IF(A36="","",A36/$B$8) | C36: =IF(A36="","",IF(A36<$E$8,$E$7,$E$7+$B$5)) | D36: =IF(A36="","",$E$9^(-$B$10*B36)) | E36: =IF(A36="","",C36*D36)
A37: =IF(19<= $E$8, 19, "") | B37: =IF(A37="","",A37/$B$8) | C37: =IF(A37="","",IF(A37<$E$8,$E$7,$E$7+$B$5)) | D37: =IF(A37="","",$E$9^(-$B$10*B37)) | E37: =IF(A37="","",C37*D37)
A38: =IF(20<= $E$8, 20, "") | B38: =IF(A38="","",A38/$B$8) | C38: =IF(A38="","",IF(A38<$E$8,$E$7,$E$7+$B$5)) | D38: =IF(A38="","",$E$9^(-$B$10*B38)) | E38: =IF(A38="","",C38*D38)
A39: =IF(21<= $E$8, 21, "") | B39: =IF(A39="","",A39/$B$8) | C39: =IF(A39="","",IF(A39<$E$8,$E$7,$E$7+$B$5)) | D39: =IF(A39="","",$E$9^(-$B$10*B39)) | E39: =IF(A39="","",C39*D39)
A40: =IF(22<= $E$8, 22, "") | B40: =IF(A40="","",A40/$B$8) | C40: =IF(A40="","",IF(A40<$E$8,$E$7,$E$7+$B$5)) | D40: =IF(A40="","",$E$9^(-$B$10*B40)) | E40: =IF(A40="","",C40*D40)
A41: =IF(23<= $E$8, 23, "") | B41: =IF(A41="","",A41/$B$8) | C41: =IF(A41="","",IF(A41<$E$8,$E$7,$E$7+$B$5)) | D41: =IF(A41="","",$E$9^(-$B$10*B41)) | E41: =IF(A41="","",C41*D41)
A42: =IF(24<= $E$8, 24, "") | B42: =IF(A42="","",A42/$B$8) | C42: =IF(A42="","",IF(A42<$E$8,$E$7,$E$7+$B$5)) | D42: =IF(A42="","",$E$9^(-$B$10*B42)) | E42: =IF(A42="","",C42*D42)
A43: =IF(25<= $E$8, 25, "") | B43: =IF(A43="","",A43/$B$8) | C43: =IF(A43="","",IF(A43<$E$8,$E$7,$E$7+$B$5)) | D43: =IF(A43="","",$E$9^(-$B$10*B43)) | E43: =IF(A43="","",C43*D43)
A44: =IF(26<= $E$8, 26, "") | B44: =IF(A44="","",A44/$B$8) | C44: =IF(A44="","",IF(A44<$E$8,$E$7,$E$7+$B$5)) | D44: =IF(A44="","",$E$9^(-$B$10*B44)) | E44: =IF(A44="","",C44*D44)
A45: =IF(27<= $E$8, 27, "") | B45: =IF(A45="","",A45/$B$8) | C45: =IF(A45="","",IF(A45<$E$8,$E$7,$E$7+$B$5)) | D45: =IF(A45="","",$E$9^(-$B$10*B45)) | E45: =IF(A45="","",C45*D45)
A46: =IF(28<= $E$8, 28, "") | B46: =IF(A46="","",A46/$B$8) | C46: =IF(A46="","",IF(A46<$E$8,$E$7,$E$7+$B$5)) | D46: =IF(A46="","",$E$9^(-$B$10*B46)) | E46: =IF(A46="","",C46*D46)
A47: =IF(29<= $E$8, 29, "") | B47: =IF(A47="","",A47/$B$8) | C47: =IF(A47="","",IF(A47<$E$8,$E$7,$E$7+$B$5)) | D47: =IF(A47="","",$E$9^(-$B$10*B47)) | E47: =IF(A47="","",C47*D47)
A48: =IF(30<= $E$8, 30, "") | B48: =IF(A48="","",A48/$B$8) | C48: =IF(A48="","",IF(A48<$E$8,$E$7,$E$7+$B$5)) | D48: =IF(A48="","",$E$9^(-$B$10*B48)) | E48: =IF(A48="","",C48*D48)
A49: =IF(31<= $E$8, 31, "") | B49: =IF(A49="","",A49/$B$8) | C49: =IF(A49="","",IF(A49<$E$8,$E$7,$E$7+$B$5)) | D49: =IF(A49="","",$E$9^(-$B$10*B49)) | E49: =IF(A49="","",C49*D49)
A50: =IF(32<= $E$8, 32, "") | B50: =IF(A50="","",A50/$B$8) | C50: =IF(A50="","",IF(A50<$E$8,$E$7,$E$7+$B$5)) | D50: =IF(A50="","",$E$9^(-$B$10*B50)) | E50: =IF(A50="","",C50*D50)
A51: =IF(33<= $E$8, 33, "") | B51: =IF(A51="","",A51/$B$8) | C51: =IF(A51="","",IF(A51<$E$8,$E$7,$E$7+$B$5)) | D51: =IF(A51="","",$E$9^(-$B$10*B51)) | E51: =IF(A51="","",C51*D51)
A52: =IF(34<= $E$8, 34, "") | B52: =IF(A52="","",A52/$B$8) | C52: =IF(A52="","",IF(A52<$E$8,$E$7,$E$7+$B$5)) | D52: =IF(A52="","",$E$9^(-$B$10*B52)) | E52: =IF(A52="","",C52*D52)
A53: =IF(35<= $E$8, 35, "") | B53: =IF(A53="","",A53/$B$8) | C53: =IF(A53="","",IF(A53<$E$8,$E$7,$E$7+$B$5)) | D53: =IF(A53="","",$E$9^(-$B$10*B53)) | E53: =IF(A53="","",C53*D53)
A54: =IF(36<= $E$8, 36, "") | B54: =IF(A54="","",A54/$B$8) | C54: =IF(A54="","",IF(A54<$E$8,$E$7,$E$7+$B$5)) | D54: =IF(A54="","",$E$9^(-$B$10*B54)) | E54: =IF(A54="","",C54*D54)
A55: =IF(37<= $E$8, 37, "") | B55: =IF(A55="","",A55/$B$8) | C55: =IF(A55="","",IF(A55<$E$8,$E$7,$E$7+$B$5)) | D55: =IF(A55="","",$E$9^(-$B$10*B55)) | E55: =IF(A55="","",C55*D55)
A56: =IF(38<= $E$8, 38, "") | B56: =IF(A56="","",A56/$B$8) | C56: =IF(A56="","",IF(A56<$E$8,$E$7,$E$7+$B$5)) | D56: =IF(A56="","",$E$9^(-$B$10*B56)) | E56: =IF(A56="","",C56*D56)
A57: =IF(39<= $E$8, 39, "") | B57: =IF(A57="","",A57/$B$8) | C57: =IF(A57="","",IF(A57<$E$8,$E$7,$E$7+$B$5)) | D57: =IF(A57="","",$E$9^(-$B$10*B57)) | E57: =IF(A57="","",C57*D57)
A58: =IF(40<= $E$8, 40, "") | B58: =IF(A58="","",A58/$B$8) | C58: =IF(A58="","",IF(A58<$E$8,$E$7,$E$7+$B$5)) | D58: =IF(A58="","",$E$9^(-$B$10*B58)) | E58: =IF(A58="","",C58*D58)
A59: =IF(41<= $E$8, 41, "") | B59: =IF(A59="","",A59/$B$8) | C59: =IF(A59="","",IF(A59<$E$8,$E$7,$E$7+$B$5)) | D59: =IF(A59="","",$E$9^(-$B$10*B59)) | E59: =IF(A59="","",C59*D59)
A60: =IF(42<= $E$8, 42, "") | B60: =IF(A60="","",A60/$B$8) | C60: =IF(A60="","",IF(A60<$E$8,$E$7,$E$7+$B$5)) | D60: =IF(A60="","",$E$9^(-$B$10*B60)) | E60: =IF(A60="","",C60*D60)
A61: =IF(43<= $E$8, 43, "") | B61: =IF(A61="","",A61/$B$8) | C61: =IF(A61="","",IF(A61<$E$8,$E$7,$E$7+$B$5)) | D61: =IF(A61="","",$E$9^(-$B$10*B61)) | E61: =IF(A61="","",C61*D61)
A62: =IF(44<= $E$8, 44, "") | B62: =IF(A62="","",A62/$B$8) | C62: =IF(A62="","",IF(A62<$E$8,$E$7,$E$7+$B$5)) | D62: =IF(A62="","",$E$9^(-$B$10*B62)) | E62: =IF(A62="","",C62*D62)
A63: =IF(45<= $E$8, 45, "") | B63: =IF(A63="","",A63/$B$8) | C63: =IF(A63="","",IF(A63<$E$8,$E$7,$E$7+$B$5)) | D63: =IF(A63="","",$E$9^(-$B$10*B63)) | E63: =IF(A63="","",C63*D63)
A64: =IF(46<= $E$8, 46, "") | B64: =IF(A64="","",A64/$B$8) | C64: =IF(A64="","",IF(A64<$E$8,$E$7,$E$7+$B$5)) | D64: =IF(A64="","",$E$9^(-$B$10*B64)) | E64: =IF(A64="","",C64*D64)
A65: =IF(47<= $E$8, 47, "") | B65: =IF(A65="","",A65/$B$8) | C65: =IF(A65="","",IF(A65<$E$8,$E$7,$E$7+$B$5)) | D65: =IF(A65="","",$E$9^(-$B$10*B65)) | E65: =IF(A65="","",C65*D65)
A66: =IF(48<= $E$8, 48, "") | B66: =IF(A66="","",A66/$B$8) | C66: =IF(A66="","",IF(A66<$E$8,$E$7,$E$7+$B$5)) | D66: =IF(A66="","",$E$9^(-$B$10*B66)) | E66: =IF(A66="","",C66*D66)
A67: =IF(49<= $E$8, 49, "") | B67: =IF(A67="","",A67/$B$8) | C67: =IF(A67="","",IF(A67<$E$8,$E$7,$E$7+$B$5)) | D67: =IF(A67="","",$E$9^(-$B$10*B67)) | E67: =IF(A67="","",C67*D67)
A68: =IF(50<= $E$8, 50, "") | B68: =IF(A68="","",A68/$B$8) | C68: =IF(A68="","",IF(A68<$E$8,$E$7,$E$7+$B$5)) | D68: =IF(A68="","",$E$9^(-$B$10*B68)) | E68: =IF(A68="","",C68*D68)
A69: =IF(51<= $E$8, 51, "") | B69: =IF(A69="","",A69/$B$8) | C69: =IF(A69="","",IF(A69<$E$8,$E$7,$E$7+$B$5)) | D69: =IF(A69="","",$E$9^(-$B$10*B69)) | E69: =IF(A69="","",C69*D69)
A70: =IF(52<= $E$8, 52, "") | B70: =IF(A70="","",A70/$B$8) | C70: =IF(A70="","",IF(A70<$E$8,$E$7,$E$7+$B$5)) | D70: =IF(A70="","",$E$9^(-$B$10*B70)) | E70: =IF(A70="","",C70*D70)
A71: =IF(53<= $E$8, 53, "") | B71: =IF(A71="","",A71/$B$8) | C71: =IF(A71="","",IF(A71<$E$8,$E$7,$E$7+$B$5)) | D71: =IF(A71="","",$E$9^(-$B$10*B71)) | E71: =IF(A71="","",C71*D71)
A72: =IF(54<= $E$8, 54, "") | B72: =IF(A72="","",A72/$B$8) | C72: =IF(A72="","",IF(A72<$E$8,$E$7,$E$7+$B$5)) | D72: =IF(A72="","",$E$9^(-$B$10*B72)) | E72: =IF(A72="","",C72*D72)
A73: =IF(55<= $E$8, 55, "") | B73: =IF(A73="","",A73/$B$8) | C73: =IF(A73="","",IF(A73<$E$8,$E$7,$E$7+$B$5)) | D73: =IF(A73="","",$E$9^(-$B$10*B73)) | E73: =IF(A73="","",C73*D73)
A74: =IF(56<= $E$8, 56, "") | B74: =IF(A74="","",A74/$B$8) | C74: =IF(A74="","",IF(A74<$E$8,$E$7,$E$7+$B$5)) | D74: =IF(A74="","",$E$9^(-$B$10*B74)) | E74: =IF(A74="","",C74*D74)
A75: =IF(57<= $E$8, 57, "") | B75: =IF(A75="","",A75/$B$8) | C75: =IF(A75="","",IF(A75<$E$8,$E$7,$E$7+$B$5)) | D75: =IF(A75="","",$E$9^(-$B$10*B75)) | E75: =IF(A75="","",C75*D75)
A76: =IF(58<= $E$8, 58, "") | B76: =IF(A76="","",A76/$B$8) | C76: =IF(A76="","",IF(A76<$E$8,$E$7,$E$7+$B$5)) | D76: =IF(A76="","",$E$9^(-$B$10*B76)) | E76: =IF(A76="","",C76*D76)
A77: =IF(59<= $E$8, 59, "") | B77: =IF(A77="","",A77/$B$8) | C77: =IF(A77="","",IF(A77<$E$8,$E$7,$E$7+$B$5)) | D77: =IF(A77="","",$E$9^(-$B$10*B77)) | E77: =IF(A77="","",C77*D77)
A78: =IF(60<= $E$8, 60, "") | B78: =IF(A78="","",A78/$B$8) | C78: =IF(A78="","",IF(A78<$E$8,$E$7,$E$7+$B$5)) | D78: =IF(A78="","",$E$9^(-$B$10*B78)) | E78: =IF(A78="","",C78*D78)
A79: =IF(61<= $E$8, 61, "") | B79: =IF(A79="","",A79/$B$8) | C79: =IF(A79="","",IF(A79<$E$8,$E$7,$E$7+$B$5)) | D79: =IF(A79="","",$E$9^(-$B$10*B79)) | E79: =IF(A79="","",C79*D79)
A80: =IF(62<= $E$8, 62, "") | B80: =IF(A80="","",A80/$B$8) | C80: =IF(A80="","",IF(A80<$E$8,$E$7,$E$7+$B$5)) | D80: =IF(A80="","",$E$9^(-$B$10*B80)) | E80: =IF(A80="","",C80*D80)
A81: =IF(63<= $E$8, 63, "") | B81: =IF(A81="","",A81/$B$8) | C81: =IF(A81="","",IF(A81<$E$8,$E$7,$E$7+$B$5)) | D81: =IF(A81="","",$E$9^(-$B$10*B81)) | E81: =IF(A81="","",C81*D81)
A82: =IF(64<= $E$8, 64, "") | B82: =IF(A82="","",A82/$B$8) | C82: =IF(A82="","",IF(A82<$E$8,$E$7,$E$7+$B$5)) | D82: =IF(A82="","",$E$9^(-$B$10*B82)) | E82: =IF(A82="","",C82*D82)
A83: =IF(65<= $E$8, 65, "") | B83: =IF(A83="","",A83/$B$8) | C83: =IF(A83="","",IF(A83<$E$8,$E$7,$E$7+$B$5)) | D83: =IF(A83="","",$E$9^(-$B$10*B83)) | E83: =IF(A83="","",C83*D83)
A84: =IF(66<= $E$8, 66, "") | B84: =IF(A84="","",A84/$B$8) | C84: =IF(A84="","",IF(A84<$E$8,$E$7,$E$7+$B$5)) | D84: =IF(A84="","",$E$9^(-$B$10*B84)) | E84: =IF(A84="","",C84*D84)
A85: =IF(67<= $E$8, 67, "") | B85: =IF(A85="","",A85/$B$8) | C85: =IF(A85="","",IF(A85<$E$8,$E$7,$E$7+$B$5)) | D85: =IF(A85="","",$E$9^(-$B$10*B85)) | E85: =IF(A85="","",C85*D85)
A86: =IF(68<= $E$8, 68, "") | B86: =IF(A86="","",A86/$B$8) | C86: =IF(A86="","",IF(A86<$E$8,$E$7,$E$7+$B$5)) | D86: =IF(A86="","",$E$9^(-$B$10*B86)) | E86: =IF(A86="","",C86*D86)
A87: =IF(69<= $E$8, 69, "") | B87: =IF(A87="","",A87/$B$8) | C87: =IF(A87="","",IF(A87<$E$8,$E$7,$E$7+$B$5)) | D87: =IF(A87="","",$E$9^(-$B$10*B87)) | E87: =IF(A87="","",C87*D87)
A88: =IF(70<= $E$8, 70, "") | B88: =IF(A88="","",A88/$B$8) | C88: =IF(A88="","",IF(A88<$E$8,$E$7,$E$7+$B$5)) | D88: =IF(A88="","",$E$9^(-$B$10*B88)) | E88: =IF(A88="","",C88*D88)
A89: =IF(71<= $E$8, 71, "") | B89: =IF(A89="","",A89/$B$8) | C89: =IF(A89="","",IF(A89<$E$8,$E$7,$E$7+$B$5)) | D89: =IF(A89="","",$E$9^(-$B$10*B89)) | E89: =IF(A89="","",C89*D89)
A90: =IF(72<= $E$8, 72, "") | B90: =IF(A90="","",A90/$B$8) | C90: =IF(A90="","",IF(A90<$E$8,$E$7,$E$7+$B$5)) | D90: =IF(A90="","",$E$9^(-$B$10*B90)) | E90: =IF(A90="","",C90*D90)
A91: =IF(73<= $E$8, 73, "") | B91: =IF(A91="","",A91/$B$8) | C91: =IF(A91="","",IF(A91<$E$8,$E$7,$E$7+$B$5)) | D91: =IF(A91="","",$E$9^(-$B$10*B91)) | E91: =IF(A91="","",C91*D91)
A92: =IF(74<= $E$8, 74, "") | B92: =IF(A92="","",A92/$B$8) | C92: =IF(A92="","",IF(A92<$E$8,$E$7,$E$7+$B$5)) | D92: =IF(A92="","",$E$9^(-$B$10*B92)) | E92: =IF(A92="","",C92*D92)
A93: =IF(75<= $E$8, 75, "") | B93: =IF(A93="","",A93/$B$8) | C93: =IF(A93="","",IF(A93<$E$8,$E$7,$E$7+$B$5)) | D93: =IF(A93="","",$E$9^(-$B$10*B93)) | E93: =IF(A93="","",C93*D93)
A94: =IF(76<= $E$8, 76, "") | B94: =IF(A94="","",A94/$B$8) | C94: =IF(A94="","",IF(A94<$E$8,$E$7,$E$7+$B$5)) | D94: =IF(A94="","",$E$9^(-$B$10*B94)) | E94: =IF(A94="","",C94*D94)
A95: =IF(77<= $E$8, 77, "") | B95: =IF(A95="","",A95/$B$8) | C95: =IF(A95="","",IF(A95<$E$8,$E$7,$E$7+$B$5)) | D95: =IF(A95="","",$E$9^(-$B$10*B95)) | E95: =IF(A95="","",C95*D95)
A96: =IF(78<= $E$8, 78, "") | B96: =IF(A96="","",A96/$B$8) | C96: =IF(A96="","",IF(A96<$E$8,$E$7,$E$7+$B$5)) | D96: =IF(A96="","",$E$9^(-$B$10*B96)) | E96: =IF(A96="","",C96*D96)
A97: =IF(79<= $E$8, 79, "") | B97: =IF(A97="","",A97/$B$8) | C97: =IF(A97="","",IF(A97<$E$8,$E$7,$E$7+$B$5)) | D97: =IF(A97="","",$E$9^(-$B$10*B97)) | E97: =IF(A97="","",C97*D97)
A98: =IF(80<= $E$8, 80, "") | B98: =IF(A98="","",A98/$B$8) | C98: =IF(A98="","",IF(A98<$E$8,$E$7,$E$7+$B$5)) | D98: =IF(A98="","",$E$9^(-$B$10*B98)) | E98: =IF(A98="","",C98*D98)
A99: =IF(81<= $E$8, 81, "") | B99: =IF(A99="","",A99/$B$8) | C99: =IF(A99="","",IF(A99<$E$8,$E$7,$E$7+$B$5)) | D99: =IF(A99="","",$E$9^(-$B$10*B99)) | E99: =IF(A99="","",C99*D99)
A100: =IF(82<= $E$8, 82, "") | B100: =IF(A100="","",A100/$B$8) | C100: =IF(A100="","",IF(A100<$E$8,$E$7,$E$7+$B$5)) | D100: =IF(A100="","",$E$9^(-$B$10*B100)) | E100: =IF(A100="","",C100*D100)
A101: =IF(83<= $E$8, 83, "") | B101: =IF(A101="","",A101/$B$8) | C101: =IF(A101="","",IF(A101<$E$8,$E$7,$E$7+$B$5)) | D101: =IF(A101="","",$E$9^(-$B$10*B101)) | E101: =IF(A101="","",C101*D101)
A102: =IF(84<= $E$8, 84, "") | B102: =IF(A102="","",A102/$B$8) | C102: =IF(A102="","",IF(A102<$E$8,$E$7,$E$7+$B$5)) | D102: =IF(A102="","",$E$9^(-$B$10*B102)) | E102: =IF(A102="","",C102*D102)
...

Sheet Help
A1: How to use this workbook
A3: 1) Inputs: fill Face Value, coupon rate, maturity (years), coupon frequency p, nominal yield j^(m), and compounding m. 2) Outputs update automatically: Price, Macaulay duration, modified duration, convexity. 3) Cash-Flow table shows time t (years), CF, discount factor (1+j/m)^(-m t), and PV. 4) Scenario table: install VBA module RunScenarios.bas then click the button to batch-run shocks. Notes: - Time is in years. j^(m) means nominal rate convertible m times per year. - If T*p is not an integer, adjust T or p so number of payments N is an integer. - To model irregular cash flows, you can overwrite the Cash Flow column values manually (and optionally Time). Price/duration/convexity will then reflect those edited cash flows (but the VBA scenario runner uses the standard bond schedule).

Sheet Curve
A1: Tenor (years) | B1: Zero rate j^(m) (decimal) | C1: Note
A2: 0.5 | B2: ='Bond Toolkit'!$B$9 | C2: Default: flat curve from template yield
A3: 1 | B3: ='Bond Toolkit'!$B$9 | C3: Default: flat curve from template yield
A4: 2 | B4: ='Bond Toolkit'!$B$9 | C4: Default: flat curve from template yield
A5: 5 | B5: ='Bond Toolkit'!$B$9 | C5: Default: flat curve from template yield
A6: 10 | B6: ='Bond Toolkit'!$B$9 | C6: Default: flat curve from template yield
A7: 20 | B7: ='Bond Toolkit'!$B$9 | C7: Default: flat curve from template yield
A8: 30 | B8: ='Bond Toolkit'!$B$9 | C8: Default: flat curve from template yield
